[{"index": 0, "text": "Death Valley National Park", "start": 1.081, "end": 2.961, "zh": "死亡谷国家公园"}, {"index": 1, "text": "Elsewhere in the Mojave,", "start": 18.189, "end": 19.69, "zh": "在莫哈韦沙漠的其他地方"}, {"index": 2, "text": "just north of Joshua Tree, A seemingly endless noon grills a vast expanse of barren dunes.", "start": 20.53, "end": 29.055, "zh": "就在约书亚树国家公园以北，仿佛无尽的正午骄阳炙烤着一片广袤荒芜的沙丘。"}, {"index": 3, "text": "Lying far below sea level, this is Death Valley, the most exotic of our national parks.", "start": 31.516, "end": 39.58, "zh": "这里远低于海平面，就是死亡谷，我们国家公园中最奇异的一处。"}, {"index": 4, "text": "East of the Sierra Nevada, between the arid Great Basin and the Mojave, this is the largest park in the contiguous United States.", "start": 41.641, "end": 50.365, "zh": "它位于内华达山脉以东，介于干旱的大盆地与莫哈韦沙漠之间，是美国本土面积最大的国家公园。"}, {"index": 5, "text": "Though there's often snow on the distant Paramount Mountains, it can be the hottest place in North America.", "start": 56.389, "end": 62.912, "zh": "尽管远处的帕拉蒙山脉常常白雪皑皑，这里却可能是北美洲最炎热的地方。"}, {"index": 6, "text": "In August, a brutal 120 degrees Fahrenheit in the shade, if shade can be found.", "start": 65.013, "end": 71.977, "zh": "八月里，即便找得到阴凉处，阴凉下也高达华氏120度，酷热难耐。"}, {"index": 7, "text": "Hot enough to melt a pair of shoes.", "start": 74.659, "end": 77.44, "zh": "炎热到足以把一双鞋子融化。"}, {"index": 8, "text": "A sign at Badwater Basin marks the lowest spot on the continent.", "start": 86.581, "end": 91.063, "zh": "恶水盆地的一块标牌标示出北美大陆的最低点。"}, {"index": 9, "text": "A drop from Death Valley's highest mountain, 11 ,049 -foot telescope peak to Badwater Basin, is twice the depth of Grand Canyon.", "start": 93.324, "end": 103.209, "zh": "从死亡谷海拔11049英尺的最高峰望远镜峰，一直落到恶水盆地，其落差是大峡谷的两倍。"}, {"index": 10, "text": "There were large lakes here once, in the prehistoric past.", "start": 108.091, "end": 114.074, "zh": "史前时代，这里曾有大片湖泊。"}, {"index": 11, "text": "But the Earth's climates changed, and the lakes dried up.", "start": 117.336, "end": 122.338, "zh": "但地球气候变迁，湖泊逐渐干涸。"}, {"index": 12, "text": "Yet, Death Valley exudes a strange beauty all its own.", "start": 124.479, "end": 128.121, "zh": "然而，死亡谷依然散发着一种独特的怪异之美。"}, {"index": 13, "text": "As America's poet Mark Strand has discovered, its million -plus areas of yellows,", "start": 130.623, "end": 136.666, "zh": "正如美国诗人马克·斯特兰德所发现的，这里绵延超过百万英亩的黄色、"}, {"index": 14, "text": "oranges, The orange, faint reds and purple smudges of manganese suggest a Martian landscape, or what we believe the reaches of Mars to be like.", "start": 136.666, "end": 148.692, "zh": "橙色、淡红色以及锰矿留下的紫色斑迹，让人联想到火星地貌，或者说我们想象中火星的样子。"}, {"index": 15, "text": "Precious water from rare desert springs sustains wildlife.", "start": 159.198, "end": 163.3, "zh": "稀少的沙漠泉水滋养着这里的野生动物，弥足珍贵。"}, {"index": 16, "text": "Humans were drawn here in the 1900s by the land's mineral wealth.", "start": 167.36, "end": 171.282, "zh": "20世纪初，人们因这片土地丰富的矿产资源而被吸引至此。"}, {"index": 17, "text": "Mines were constructed.", "start": 172.283, "end": 173.803, "zh": "矿场由此建起。"}, {"index": 18, "text": "Borax, a mineral with many industrial uses, was extracted from the ancient salt crusts lining the lakes that had once shimmered here.", "start": 174.264, "end": 182.608, "zh": "硼砂——一种用途广泛的工业矿物——被从曾经波光粼粼的湖泊边缘的古老盐壳中提炼出来。"}, {"index": 19, "text": "The borax was hauled to the railroad in huge 20 -mule team wagons.", "start": 187.191, "end": 191.232, "zh": "硼砂由巨大的二十骡队马车运往铁路。"}, {"index": 20, "text": "Tent City sprang up, which gave way to settlements of wood and stone.", "start": 196.615, "end": 205.5, "zh": "帐篷小镇由此兴起，后来又被木石建筑的定居点取代。"}, {"index": 21, "text": "Rhyolite is one of them.", "start": 209.78, "end": 211.461, "zh": "莱奥莱特就是其中之一。"}, {"index": 22, "text": "Today, Rhyolite, just outside the park, is a ghost town, and well worth a visit.", "start": 213.642, "end": 219.725, "zh": "如今，位于公园之外的莱奥莱特已成为一座鬼城，非常值得一游。"}, {"index": 23, "text": "Now these ghost towns bleach in the torrid sun, until one day they simply fade back into into the desert.", "start": 226.849, "end": 236.834, "zh": "这些鬼城如今在酷烈的阳光下逐渐褪色，终有一天会悄然消融回沙漠之中。"}, {"index": 24, "text": "But all isn't ghostly.", "start": 239.415, "end": 241.136, "zh": "但并非一切都如鬼魅般死寂。"}, {"index": 25, "text": "After a lengthy stretch of bareness, of raw, harsh wasteland, a visitor encounters this.", "start": 245.298, "end": 252.602, "zh": "穿过一段漫长荒芜、粗粝严酷的旷野之后，游客会遇见这样一处景象。"}, {"index": 26, "text": "it isn't a mirage or a sign of sunstroke.", "start": 266.469, "end": 270.25, "zh": "它不是海市蜃楼，也不是中暑产生的幻觉。"}, {"index": 27, "text": "This architectural hybrid, part Spanish, part Mediterranean, part Hollywood -backed lot, is Scotty's Castle, the most famous man -made attraction in Death Valley.", "start": 271.491, "end": 283.817, "zh": "这座融合了西班牙风格、地中海风情与好莱坞片场气息的建筑，就是斯科蒂城堡，死亡谷里最著名的人造景观。"}, {"index": 28, "text": "Though he never really owned it, it's named after Death Valley Scotty, the wildest two -legged critter ever to dwell in these parts.", "start": 287.939, "end": 295.704, "zh": "虽然他从未真正拥有过它，这座城堡却以“死亡谷斯科蒂”命名——他是曾在这片土地上生活过的最狂野的人物。"}, {"index": 29, "text": "As a young cowboy, Scotty travels with Buffalo Bill's Wild West show, performing as a trick rider and sharpshooter.", "start": 298.986, "end": 307.23, "zh": "斯科蒂年轻时曾在“水牛比尔”的荒野西部表演团里当牛仔，表演特技骑术和神枪手绝技。"}, {"index": 30, "text": "But these aren't Scotty's only talents.", "start": 307.75, "end": 309.971, "zh": "但这并非斯科蒂唯一的才能。"}, {"index": 31, "text": "He has an inborn knack for, you might say, playing tricks with the truth.", "start": 310.632, "end": 315.914, "zh": "他天生擅长——可以说——在真相上玩花样。"}, {"index": 32, "text": "Plain folks call it lying.", "start": 317.515, "end": 319.636, "zh": "老百姓则直接称之为撒谎。"}, {"index": 33, "text": "One of his imaginary grub stakes is a pie -in -the -sky gold mine in a little -known valley.", "start": 321.037, "end": 326.46, "zh": "他编造的众多虚构财富之一，就是一处鲜为人知的山谷中一座“画饼充饥”式的金矿。"}, {"index": 34, "text": "Well, Scotty goes east to Chicago to sell shares in his pipe dream mine to unsuspecting businessmen.", "start": 329.001, "end": 335.964, "zh": "于是，斯科蒂前往东部的芝加哥，向毫不知情的商人们兜售他那虚构金矿的股份。"}, {"index": 35, "text": "As luck would have it, he peddles a third of the shares to Albert Johnson, the wealthy president of the National Life Insurance Company.", "start": 336.904, "end": 345.088, "zh": "机缘巧合下，他把三分之一的股份卖给了阿尔伯特·约翰逊——国民人寿保险公司的富有总裁。"}, {"index": 36, "text": "Scotty had corralled a real sucker.", "start": 345.569, "end": 347.729, "zh": "斯科蒂这次真是钓到了一条大鱼。"}, {"index": 37, "text": "Poor Johnson hadn't seen so much as a single gold nugget.", "start": 347.77, "end": 351.611, "zh": "可怜的约翰逊连一块金块都没见过。"}, {"index": 38, "text": "Pleased with himself, Scotty returns to Death Valley, leaving the swindled Albert Johnson behind in Chicago.", "start": 352.612, "end": 359.495, "zh": "斯科蒂洋洋得意地返回死亡谷，把被骗的阿尔伯特·约翰逊留在了芝加哥。"}, {"index": 39, "text": "Or does he?", "start": 360.816, "end": 361.816, "zh": "事情真的就此结束了吗？"}, {"index": 40, "text": "A telegram reaches Scotty.", "start": 362.897, "end": 364.658, "zh": "一封电报送到了斯科蒂手中。"}, {"index": 41, "text": "Albert Johnson is coming to Death Valley to see for himself this gold mine of which he is now part owner.", "start": 365.799, "end": 372.202, "zh": "阿尔伯特·约翰逊要亲自前往死亡谷，看看这座他如今已成为股东的金矿。"}, {"index": 42, "text": "Scotty's alarmed, but can't this weigh Johnson from coming out?", "start": 373.603, "end": 377.585, "zh": "斯科蒂惊慌失措，但又怎能阻止约翰逊前来呢？"}, {"index": 43, "text": "En route to Death Valley, Albert Johnson and Scotty are halted by masked bandits.", "start": 378.945, "end": 383.808, "zh": "在前往死亡谷的路上，阿尔伯特·约翰逊和斯科蒂被蒙面强盗拦下。"}, {"index": 44, "text": "It's a holdup.", "start": 384.208, "end": 385.348, "zh": "这是一场打劫。"}, {"index": 45, "text": "Rumor has it that Scotty had the holdup staged as a delaying tactic.", "start": 386.889, "end": 390.751, "zh": "有传言说，这场打劫其实是斯科蒂自导自演，用来拖延时间的手段。"}, {"index": 46, "text": "In any case, Johnson returns to Chicago, never having seen the bogus gold mine.", "start": 391.972, "end": 397.715, "zh": "不管怎样，约翰逊最终返回芝加哥，始终没能见到那座根本不存在的金矿。"}, {"index": 47, "text": "But Johnson makes another trip.", "start": 399.476, "end": 401.256, "zh": "但约翰逊又来了一次。"}, {"index": 48, "text": "Scotty's beside himself.", "start": 402.457, "end": 404.218, "zh": "斯科蒂顿时慌了神。"}, {"index": 49, "text": "It seems that Johnson has some serious health problems and finds the desert air healing.", "start": 405.439, "end": 411.642, "zh": "原来，约翰逊身患一些严重的健康问题，而沙漠的空气让他感到疗愈。"}, {"index": 50, "text": "As a matter of fact, he hasn't felt so well in years as he does in Death Valley.", "start": 414.364, "end": 418.926, "zh": "事实上，他多年来从未像在死亡谷这样感觉如此良好。"}, {"index": 51, "text": "His visits become longer and more frequent.", "start": 420.187, "end": 422.688, "zh": "他来访的次数越来越频繁，逗留的时间也越来越长。"}, {"index": 52, "text": "And soon he's bringing his wife Bessie along with him.", "start": 423.468, "end": 426.309, "zh": "很快，他把妻子贝西也带来了。"}, {"index": 53, "text": "Bessie too likes the desert but she dislikes sleeping in a tent among rattlesnakes and scorpions.", "start": 427.69, "end": 433.193, "zh": "贝西同样喜欢这片沙漠，但她不喜欢睡在满是响尾蛇和蝎子的帐篷里。"}, {"index": 54, "text": "Bessie wants something more comfortable.", "start": 435.394, "end": 438.196, "zh": "贝西想要更舒适的居所。"}, {"index": 55, "text": "And so in the 1920s construction begins on what comes to be called Scotty's Castle.", "start": 439.817, "end": 446.58, "zh": "于是在20世纪20年代，后来被称为“斯科蒂城堡”的建筑工程开始动工。"}, {"index": 56, "text": "Today, you can tour the opulently furnished rooms, the great hall,", "start": 454.761, "end": 463.064, "zh": "如今，游客可以参观其中陈设奢华的房间、宏伟的大厅，"}, {"index": 57, "text": "and the music room with its theater organ of 1 ,121 pipes.", "start": 466.366, "end": 473.19, "zh": "以及配有1121根管风琴的音乐厅。"}, {"index": 58, "text": "The Johnsons allow their mansion to be called Scotty's Castle.", "start": 474.911, "end": 479.533, "zh": "约翰逊夫妇允许人们将他们的宅邸称为“斯科蒂城堡”。"}, {"index": 59, "text": "The three of them become fast friends, and Albert Johnson lets it be known that the castle's construction was financed with profits from the gold mine, which never did exist.", "start": 481.954, "end": 493.78, "zh": "三人成了亲密的朋友，阿尔伯特·约翰逊也任由外界相信，城堡的建造资金来自那座其实从未存在过的金矿的收益。"}, {"index": 60, "text": "Though touring Scotty's Castle is a stellar attraction,", "start": 500.141, "end": 503.362, "zh": "虽然参观斯科蒂城堡是一大亮点，"}, {"index": 61, "text": "Death Valley offers sundry other activities of the kind that tone the body for the rugged during the cooler months hiking", "start": 504.163, "end": 513.687, "zh": "死亡谷在较凉爽的月份里还提供各种其他能锻炼体魄的活动，适合硬朗的旅人，"}, {"index": 62, "text": "is popular and being the Wild West horseback riding one", "start": 513.687, "end": 528.014, "zh": "徒步旅行很受欢迎，而作为昔日蛮荒西部的象征，骑马旅行"}, {"index": 63, "text": "can make Death Valley a golfing vacation with a whole new take on golf the 18 hole par 70 Furness Creek course is the world's lowest elevation golf course there's", "start": 528.014, "end": 541.511, "zh": "也能让死亡谷之行变成一场高尔夫之旅，带来全新的高尔夫体验：这座18洞、标准杆70杆的弗内斯溪高尔夫球场，是世界上海拔最低的高尔夫球场，"}, {"index": 64, "text": "a noticeable difference in how the ball response.", "start": 541.511, "end": 544.163, "zh": "球在这里的反应会有明显不同。"}, {"index": 65, "text": "This course is a challenge.", "start": 545.343, "end": 547.644, "zh": "这座球场极具挑战性。"}, {"index": 66, "text": "Seasonally the stubbornly dry desert yields to brief torrents of winter rain.", "start": 554.308, "end": 559.19, "zh": "随着季节更替，这片顽固干旱的沙漠也会迎来短暂而猛烈的冬季暴雨，"}, {"index": 67, "text": "and the desert explodes", "start": 561.151, "end": 563.392, "zh": "于是沙漠焕然一新，"}, {"index": 68, "text": "in a springtime array of exotic flowers this is Death Valley when it is most alive", "start": 567.695, "end": 578.16, "zh": "绽放出春日里绚丽多姿的奇花异卉——这正是死亡谷最富生机的时刻。"}]