[{"index": 0, "text": "This is Cumbria, home of the Lake District, England's biggest national park.", "start": 3.54, "end": 9.693, "zh": "这里是坎布里亚,英格兰最大的国家公园——湖区就坐落在此。", "zh_hant": "這裡是坎布里亞,英格蘭最大的國家公園——湖區就坐落在此。"}, {"index": 1, "text": "With its stunning countryside and pristine lakes, it draws 20 million visitors a year.", "start": 9.583, "end": 15.676, "zh": "这里风光旖旎、湖泊清澈,每年吸引两千万游客前来观光。", "zh_hant": "這裡風光旖旎、湖泊清澈,每年吸引兩千萬遊客前來觀光。"}, {"index": 2, "text": "But I'm not here for the views.", "start": 15.847, "end": 17.497, "zh": "但我来这里不是为了看风景。", "zh_hant": "但我來這裡不是為了看風景。"}, {"index": 3, "text": "I'm here because somewhere on a farm up ahead, something that hasn't been seen here for six thousand years is making a comeback.", "start": 17.347, "end": 25.041, "zh": "我来这里,是因为在前方的一处农场,一种在这里消失了六千年的动物正在重新归来。", "zh_hant": "我來這裡,是因為在前方的一處農場,一種在這裡消失了六千年的動物正在重新歸來。"}, {"index": 4, "text": "Bison, the largest land animal in Europe.", "start": 29.033, "end": 34.506, "zh": "欧洲野牛,欧洲体型最大的陆生动物。", "zh_hant": "歐洲野牛,歐洲體型最大的陸生動物。"}, {"index": 5, "text": "They can reach two meters in height and weigh as much as a car.", "start": 34.776, "end": 39.208, "zh": "它们身高可达两米,体重堪比一辆汽车。", "zh_hant": "它們身高可達兩米,體重堪比一輛汽車。"}, {"index": 6, "text": "For thousands of years, these giants roamed from Scotland to Siberia.", "start": 39.778, "end": 44.631, "zh": "数千年来,这些庞然大物曾漫游于从苏格兰到西伯利亚的广袤土地。", "zh_hant": "數千年來,這些龐然大物曾漫遊於從蘇格蘭到西伯利亞的廣袤土地。"}, {"index": 7, "text": "But by 1927, the species was hunted to extinction, and the European bison disappeared from the wild.", "start": 44.521, "end": 52.575, "zh": "但到1927年,这一物种被猎杀至灭绝,欧洲野牛从野外彻底消失。", "zh_hant": "但到1927年,這一物種被獵殺至滅絕,歐洲野牛從野外徹底消失。"}, {"index": 8, "text": "In 2022, the Wildwood Trust, a small zoo in Kent, launched an ambitious project to bring wild bison back to Britain.", "start": 53.065, "end": 62.76, "zh": "2022年,肯特郡一家小型动物园——野林信托基金,启动了一项雄心勃勃的计划,要让野生野牛重返英国。", "zh_hant": "2022年,肯特郡一家小型動物園——野林信託基金,啟動了一項雄心勃勃的計劃,要讓野生野牛重返英國。"}, {"index": 9, "text": "And today, they're releasing them in a new location for the very first time.", "start": 62.97, "end": 67.862, "zh": "而今天,他们将首次在一个全新地点放归这些野牛。", "zh_hant": "而今天,他們將首次在一個全新地點放歸這些野牛。"}, {"index": 10, "text": "Here to oversee the release is Donovan Wright, one of the only two bison rangers in the country.", "start": 69.894, "end": 76.887, "zh": "前来监督这次放归的是多诺万·赖特,他是全国仅有的两名野牛管理员之一。", "zh_hant": "前來監督這次放歸的是多諾萬·賴特,他是全國僅有的兩名野牛管理員之一。"}, {"index": 11, "text": "They are extraordinary.", "start": 76.617, "end": 84.351, "zh": "它们真是非同凡响。", "zh_hant": "它們真是非同凡響。"}, {"index": 12, "text": "The herd was transported here 30 days ago and has been in quarantine ahead of its release.", "start": 85.342, "end": 90.774, "zh": "这群野牛30天前被运到这里,一直处于隔离状态,等待放归。", "zh_hant": "這群野牛30天前被運到這裡,一直處於隔離狀態,等待放歸。"}, {"index": 13, "text": "How almost mythical.", "start": 93.746, "end": 95.296, "zh": "简直像神话一般。", "zh_hant": "簡直像神話一般。"}, {"index": 14, "text": "Tell me, Doc, why are bison so special?", "start": 96.607, "end": 99.398, "zh": "博士,请告诉我,野牛为什么如此特别?", "zh_hant": "博士,請告訴我,野牛為什麼如此特別?"}, {"index": 15, "text": "How close did we come to losing them?", "start": 99.168, "end": 101.079, "zh": "我们当初差点就永远失去它们了吗?", "zh_hant": "我們當初差點就永遠失去它們了嗎?"}, {"index": 16, "text": "They were officially extinct in the wild.", "start": 101.009, "end": 103.62, "zh": "它们曾被正式宣布为野外灭绝。", "zh_hant": "它們曾被正式宣佈為野外滅絕。"}, {"index": 17, "text": "That was it.", "start": 103.19, "end": 104.201, "zh": "就是那么彻底。", "zh_hant": "就是那麼徹底。"}, {"index": 18, "text": "But they found 54 animals that were kept in zoos and wildlife sanctuaries, and from those animals, 12 of them bred.", "start": 104.151, "end": 111.704, "zh": "但人们发现还有54头动物被圈养在动物园和野生动物保护区里,而其中有12头成功繁殖。", "zh_hant": "但人們發現還有54頭動物被圈養在動物園和野生動物保護區裡,而其中有12頭成功繁殖。"}, {"index": 19, "text": "And all... The European bison in the world today can be traced back to those 12 bison.", "start": 111.755, "end": 116.827, "zh": "如今世界上所有的欧洲野牛,都可以追溯到那12头身上。", "zh_hant": "如今世界上所有的歐洲野牛,都可以追溯到那12頭身上。"}, {"index": 20, "text": "It's history in the making.", "start": 116.897, "end": 118.668, "zh": "这是正在书写的历史。", "zh_hant": "這是正在書寫的歷史。"}, {"index": 21, "text": "The bison are being released onto 5,000 acres of farmland, where their presence will transform the ecosystem.", "start": 118.218, "end": 130.334, "zh": "这些野牛将被放归到5000英亩的农田上,它们的存在将彻底改变当地的生态系统。", "zh_hant": "這些野牛將被放歸到5000英畝的農田上,它們的存在將徹底改變當地的生態系統。"}, {"index": 22, "text": "So this is bison debarking.", "start": 133.085, "end": 136.077, "zh": "看,这就是野牛啃树皮留下的痕迹。", "zh_hant": "看,這就是野牛啃樹皮留下的痕跡。"}, {"index": 23, "text": "You can actually see the bite marks, the teeth marks.", "start": 138.188, "end": 140.839, "zh": "你能清楚看到咬痕,那些牙印。", "zh_hant": "你能清楚看到咬痕,那些牙印。"}, {"index": 24, "text": "When you see a bison debarking a tree, oh my goodness, their teeth are like chisels.", "start": 140.549, "end": 145.561, "zh": "当你亲眼看到野牛啃树皮时,天哪,它们的牙齿就像凿子一样。", "zh_hant": "當你親眼看到野牛啃樹皮時,天哪,它們的牙齒就像鑿子一樣。"}, {"index": 25, "text": "The superpower of European bison is their ability to create these micro-habitats or homes for other species.", "start": 145.692, "end": 153.565, "zh": "欧洲野牛的“超能力”就在于,它们能为其他物种创造出这些微型栖息地,也就是“家”。", "zh_hant": "歐洲野牛的“超能力”就在於,它們能為其他物種創造出這些微型棲息地,也就是“家”。"}, {"index": 26, "text": "You can imagine bats would be roosting in the cracks in the tree.", "start": 153.475, "end": 157.867, "zh": "可以想象,蝙蝠会栖息在树干的裂缝里。", "zh_hant": "可以想象,蝙蝠會棲息在樹幹的裂縫裡。"}, {"index": 27, "text": "Songbirds would make use of those hollows and nest in the sides.", "start": 157.738, "end": 161.749, "zh": "鸣禽会利用那些树洞,在树侧筑巢。", "zh_hant": "鳴禽會利用那些樹洞,在樹側築巢。"}, {"index": 28, "text": "They're kind of opening up the forest for other creatures.", "start": 161.299, "end": 164.331, "zh": "它们相当于在为其他生物“打开”森林。", "zh_hant": "它們相當於在為其他生物“開啟”森林。"}, {"index": 29, "text": "It's amazing.", "start": 163.881, "end": 165.012, "zh": "真是太神奇了。", "zh_hant": "真是太神奇了。"}, {"index": 30, "text": "With everything in place, 6,000 years of waiting is about to come to an end.", "start": 167.023, "end": 173.037, "zh": "一切准备就绪,长达六千年的等待即将画上句号。", "zh_hant": "一切準備就緒,長達六千年的等待即將畫上句號。"}, {"index": 31, "text": "I can't believe what we're about to do.", "start": 174.108, "end": 176.119, "zh": "我简直不敢相信我们即将要做的事。", "zh_hant": "我簡直不敢相信我們即將要做的事。"}, {"index": 32, "text": "It's surreal.", "start": 175.669, "end": 176.899, "zh": "感觉像是在梦里。", "zh_hant": "感覺像是在夢裡。"}, {"index": 33, "text": "We're making wild history right.", "start": 176.63, "end": 182.243, "zh": "我们正在书写野生动物的历史,对吧。", "zh_hant": "我們正在書寫野生動物的歷史,對吧。"}, {"index": 34, "text": "I'm so excited.", "start": 181.793, "end": 183.123, "zh": "我太激动了。", "zh_hant": "我太激動了。"}, {"index": 35, "text": "This is the moment that we live for.", "start": 183.014, "end": 185.065, "zh": "这正是我们为之奋斗的时刻。", "zh_hant": "這正是我們為之奮鬥的時刻。"}, {"index": 36, "text": "I mean, this is three years of hard work to get to this point.", "start": 184.795, "end": 188.667, "zh": "我是说,为了这一刻,我们付出了三年的辛勤努力。", "zh_hant": "我是說,為了這一刻,我們付出了三年的辛勤努力。"}, {"index": 37, "text": "Don, I feel like we should do this together, really.", "start": 188.657, "end": 190.568, "zh": "唐,我觉得我们真的应该一起来完成这件事。", "zh_hant": "唐,我覺得我們真的應該一起來完成這件事。"}, {"index": 38, "text": "Come on, let's do it.", "start": 190.118, "end": 191.869, "zh": "来吧,我们开始吧。", "zh_hant": "來吧,我們開始吧。"}, {"index": 39, "text": "Ready?", "start": 191.479, "end": 192.029, "zh": "准备好了吗?", "zh_hant": "準備好了嗎?"}, {"index": 40, "text": "One, two, three.", "start": 191.579, "end": 192.69, "zh": "一,二,三。", "zh_hant": "一,二,三。"}, {"index": 41, "text": "So excited.", "start": 203.721, "end": 206.352, "zh": "太激动了。", "zh_hant": "太激動了。"}, {"index": 42, "text": "There are no words.", "start": 205.902, "end": 207.252, "zh": "简直无法用语言形容。", "zh_hant": "簡直無法用語言形容。"}, {"index": 43, "text": "There's no words, right?", "start": 206.923, "end": 208.613, "zh": "真的没法用语言形容,对吧?", "zh_hant": "真的沒法用語言形容,對吧?"}, {"index": 44, "text": "Oh, look at that.", "start": 208.243, "end": 209.674, "zh": "哦,快看那儿。", "zh_hant": "哦,快看那兒。"}, {"index": 45, "text": "It's just, oh, look, he's going to have a dust bowl.", "start": 210.044, "end": 212.956, "zh": "天哪,它要在那儿打滚扬尘了。", "zh_hant": "天哪,它要在那兒打滾揚塵了。"}, {"index": 46, "text": "Immediately.", "start": 212.506, "end": 213.476, "zh": "立刻就开始了。", "zh_hant": "立刻就開始了。"}, {"index": 47, "text": "It just feels right.", "start": 213.026, "end": 218.539, "zh": "这感觉真的很对。", "zh_hant": "這感覺真的很對。"}, {"index": 48, "text": "This is where they belong, out there in the world.", "start": 218.93, "end": 221.541, "zh": "这里才是它们真正属于的地方,回归这片天地。", "zh_hant": "這裡才是它們真正屬於的地方,迴歸這片天地。"}, {"index": 49, "text": "Getting on with bison business is perfect.", "start": 222.352, "end": 224.963, "zh": "让它们自由自在地做“野牛该做的事”,真是太完美了。", "zh_hant": "讓它們自由自在地做“野牛該做的事”,真是太完美了。"}, {"index": 50, "text": "Working in conservation, guys, there's so many battles that we lose, and this is one that we won.", "start": 226.415, "end": 235.43, "zh": "从事自然保护工作的朋友们,我们输掉过太多场战役,而这一次,我们赢了。", "zh_hant": "從事自然保護工作的朋友們,我們輸掉過太多場戰役,而這一次,我們贏了。"}, {"index": 51, "text": "The Travel Show.", "start": 243.423, "end": 244.755, "zh": "《旅行秀》节目。", "zh_hant": "《旅行秀》節目。"}, {"index": 52, "text": "Your essential guide wherever you're heading.", "start": 244.526, "end": 247.302, "zh": "无论你要去哪里,这都是你不可或缺的指南。", "zh_hant": "無論你要去哪裡,這都是你不可或缺的指南。"}, {"index": 53, "text": "Every weekend on BBC News.", "start": 247.374, "end": 249.989, "zh": "每周末,BBC新闻为您呈现。", "zh_hant": "每週末,BBC新聞為您呈現。"}]