[{"index": 0, "text": "Social distancing, we've been doing that for centuries.", "start": 0.0, "end": 3.002, "zh": "社交距离,我们已经这样做了好几个世纪了。", "zh_hant": "社交距離,我們已經這樣做了好幾個世紀了。"}, {"index": 1, "text": "We don't like all that hugging and touching and all that.", "start": 4.223, "end": 6.755, "zh": "我们不喜欢那种拥抱啊、碰触啊之类的。", "zh_hant": "我們不喜歡那種擁抱啊、碰觸啊之類的。"}, {"index": 2, "text": "You know, when we see each other, just a nice bow.", "start": 6.755, "end": 8.716, "zh": "你知道吗,我们见面时,就是很有礼貌地鞠个躬。", "zh_hant": "你知道嗎,我們見面時,就是很有禮貌地鞠個躬。"}, {"index": 3, "text": "That is socially distanced.", "start": 8.716, "end": 12.118, "zh": "那就是社交距离。", "zh_hant": "那就是社交距離。"}, {"index": 4, "text": "If you're really Asian, you ever see two really Asian people, it turns into a bowing contest to see who's more respectful,", "start": 12.118, "end": 18.132, "zh": "如果你是很地道的亚洲人,你见过两个很地道的亚洲人碰面吗,那简直变成了鞠躬比赛,比谁更有礼貌,", "zh_hant": "如果你是很地道的亞洲人,你見過兩個很地道的亞洲人碰面嗎,那簡直變成了鞠躬比賽,比誰更有禮貌,"}, {"index": 5, "text": "to see who can bow lower and more away from each other until you just fold it in half and you go home.", "start": 18.653, "end": 25.257, "zh": "比谁鞠得更低、离对方更远,直到你把自己对折了才回家。", "zh_hant": "比誰鞠得更低、離對方更遠,直到你把自己對摺了才回家。"}, {"index": 6, "text": "That's social distancing, people.", "start": 26.819, "end": 28.84, "zh": "这就是社交距离,朋友们。", "zh_hant": "這就是社交距離,朋友們。"}]