[{"index": 0, "text": "Why is the new house special?", "start": 12.872, "end": 15.574}, {"index": 1, "text": "I had a letter from my sister yesterday.", "start": 18.376, "end": 20.938}, {"index": 2, "text": "She lives in Nigeria.", "start": 22.399, "end": 24.1}, {"index": 3, "text": "In her letter, she said that she would come to England next year.", "start": 25.701, "end": 30.265}, {"index": 4, "text": "If she comes, she will get a surprise.", "start": 31.566, "end": 34.468}, {"index": 5, "text": "We are now living in a beautiful new house in the country.", "start": 36.189, "end": 40.272}, {"index": 6, "text": "Work on it had begun before my sister left.", "start": 40.272, "end": 45.2}, {"index": 7, "text": "The house was completed five months ago.", "start": 46.441, "end": 49.642}, {"index": 8, "text": "In my letter, I told her that she could stay with us.", "start": 51.403, "end": 55.405}, {"index": 9, "text": "The house has many large rooms and there is a lovely garden.", "start": 56.785, "end": 61.588}, {"index": 10, "text": "It is a very modern house, so it looks strange to some people.", "start": 63.228, "end": 66.07}, {"index": 11, "text": "It must be the only modern house in the district.", "start": 66.07, "end": 67.09}]