[{"index": 0, "text": "Lesson 15", "start": 7.181, "end": 7.521}, {"index": 1, "text": "Fifty pence worth of trouble", "start": 7.521, "end": 10.162}, {"index": 2, "text": "Did George get anything for his fifty pence? What?", "start": 12.842, "end": 16.903}, {"index": 3, "text": "Children always appreciate small gifts of money.", "start": 19.584, "end": 22.284}, {"index": 4, "text": "Mum or dad, of course, provides a regular supply of pocket money, but uncles and aunts are always a source of extra income.", "start": 23.304, "end": 31.746}, {"index": 5, "text": "With some children, small sums go a long way.", "start": 33.186, "end": 36.547}, {"index": 6, "text": "If fifty pence pieces are not exchanged for sweets, they rattle for months inside money boxes.", "start": 37.927, "end": 44.228}, {"index": 7, "text": "Only very thrifty children manage to fill up a money box.", "start": 45.268, "end": 48.509}, {"index": 8, "text": "For most of them, fifty pence is a small price to pay for a nice big bar of chocolate.", "start": 49.469, "end": 54.45}, {"index": 9, "text": "My nephew, George, has a money box but it is always empty.", "start": 56.03, "end": 60.551}, {"index": 10, "text": "Very few of the fifty pence pieces and pound coins I have given him have found their way there.", "start": 61.851, "end": 67.652}, {"index": 11, "text": "I gave him fifty pence yesterday and advised him to save it.", "start": 68.852, "end": 72.833}, {"index": 12, "text": "Instead, he bought himself fifty pence worth of trouble.", "start": 73.713, "end": 77.054}, {"index": 13, "text": "On his way to the sweet shop, he dropped his fifty pence and it bounced along the pavement and then disappeared down a drain.", "start": 78.274, "end": 86.936}, {"index": 14, "text": "George took off his jacket,", "start": 88.036, "end": 89.596}, {"index": 15, "text": "rolled up his sleeves and pushed his right arm through the drain cover.", "start": 90.216, "end": 94.877}, {"index": 16, "text": "He could not find his 50 pence piece anywhere, and what is more, he could not get his arm out.", "start": 96.177, "end": 103.059}, {"index": 17, "text": "A crowd of people gathered round him and a lady rubbed his arm with soap and butter, but George was firmly stuck.", "start": 103.799, "end": 110.82}, {"index": 18, "text": "The fire brigade was called and two fire fighters freed George using a special type of grease.", "start": 111.82, "end": 118.101}, {"index": 19, "text": "George was not too upset by his experience because the lady who owns the sweet shop heard about his troubles and rewarded him with a large box of chocolates.", "start": 119.362, "end": 129.703}]