[{"index": 0, "text": "Lesson 40", "start": 6.1, "end": 6.5}, {"index": 1, "text": "Who's who", "start": 7.52, "end": 9.181}, {"index": 2, "text": "How did the policeman discover that the whole thing was a joke?", "start": 11.801, "end": 15.881}, {"index": 3, "text": "It has never been explained why university students seem to enjoy practical jokes more than anyone else.", "start": 18.561, "end": 25.441}, {"index": 4, "text": "Students specialize in a particular type of practical joke: the hoax.", "start": 26.361, "end": 31.202}, {"index": 5, "text": "Inviting the fire brigade to put out a nonexistent fire is a crude form of deception which no self-respecting student would ever indulde in.", "start": 31.922, "end": 40.902}, {"index": 6, "text": "Students often create amusing situations which are funny to everyone except the victims.", "start": 41.822, "end": 48.363}, {"index": 7, "text": "When a student recently saw two workmen using a pneumatic drill outside his university,", "start": 49.563, "end": 55.663}, {"index": 8, "text": "he immediately telephoned the police and informed them that two students dressed up as workmen", "start": 56.463, "end": 62.063}, {"index": 9, "text": "were tearing up the road with a pneumatic drill.", "start": 62.303, "end": 65.024}, {"index": 10, "text": "As soon as he had hung up, he went over to the workmen and told them that if a policeman ordered them to go away,", "start": 65.584, "end": 72.224}, {"index": 11, "text": "they were not to take him seriously.", "start": 72.704, "end": 74.504}, {"index": 12, "text": "He added that a student had dressed up as a policeman and was playing all sorts of silly jokes on people.", "start": 75.364, "end": 81.285}, {"index": 13, "text": "Both the police and the workmen were grateful to the student for this piece of advance information.", "start": 82.125, "end": 87.465}, {"index": 14, "text": "The student hid in an archway nearby where he could watch and hear everything that went on.", "start": 88.445, "end": 93.325}, {"index": 15, "text": "Sure enough, a policeman arrived on the scene and politely asked the workmen to go away.", "start": 94.025, "end": 99.286}, {"index": 16, "text": "When he received a very rude reply from one of the workmen, he threatened to remove them by force.", "start": 100.046, "end": 105.506}, {"index": 17, "text": "The workmen told him to do as he pleased and the policeman telephoned for help.", "start": 106.286, "end": 110.666}, {"index": 18, "text": "Shortly afterwards, 4 more policemen arrived and remonstrated with the workmen.", "start": 111.826, "end": 116.827}, {"index": 19, "text": "As the men refused to stop working, the police attempted to seize the pneumatic drill.", "start": 117.747, "end": 122.267}, {"index": 20, "text": "The workmen struggled fiercely and one of them lost his temper.", "start": 123.367, "end": 126.887}, {"index": 21, "text": "He threatened to call the police.", "start": 127.667, "end": 129.367}, {"index": 22, "text": "At this, the police pointed out ironically that this would hardly be necessary as the men were already under arrest.", "start": 130.267, "end": 137.868}, {"index": 23, "text": "Pretending to speak seriously, one of the workmen asked if he might make a telephone call before being taken to the station.", "start": 138.628, "end": 145.828}, {"index": 24, "text": "Permission was granted and a policeman accompanied him to a pay phone.", "start": 146.588, "end": 150.808}, {"index": 25, "text": "Only when he saw that the man was actually telephoning the police did he realize that they had all been the victims of a hoax.", "start": 151.588, "end": 159.149}]