[{"index": 0, "text": "Lesson 3 An unknown goddess", "start": 1.51, "end": 6.651, "zh": "第三课 一位不知名的女神", "zh_hant": "第三課 一位不知名的女神"}, {"index": 1, "text": "How did the archaeologists", "start": 7.651, "end": 13.572, "zh": "考古学家们是怎样", "zh_hant": "考古學家們是怎樣"}, {"index": 2, "text": "know", "start": 13.612, "end": 14.032, "zh": "知道", "zh_hant": "知道"}, {"index": 3, "text": "that the statue was a goddess?", "start": 14.032, "end": 15.992, "zh": "这座雕像是一位女神的呢?", "zh_hant": "這座雕像是一位女神的呢?"}, {"index": 4, "text": "Some time ago, an interesting discovery was made by archaeologists", "start": 18.613, "end": 23.013, "zh": "不久前,考古学家们有了一个有趣的发现", "zh_hant": "不久前,考古學家們有了一個有趣的發現"}, {"index": 5, "text": "on the Aegean island of Kea.", "start": 23.073, "end": 24.953, "zh": "地点是在爱琴海的基亚岛上。", "zh_hant": "地點是在愛琴海的基亞島上。"}, {"index": 6, "text": "An American team explored a temple which stands", "start": 26.334, "end": 30.284, "zh": "一支美国考古队探查了一座神庙", "zh_hant": "一支美國考古隊探查了一座神廟"}, {"index": 7, "text": "in an ancient city on the promontory of Ayia Irini.", "start": 30.284, "end": 33.955, "zh": "这座神庙位于阿伊亚·伊里尼海岬上一座古城之中。", "zh_hant": "這座神廟位於阿伊亞·伊里尼海岬上一座古城之中。"}, {"index": 8, "text": "The city at one time must have been prosperous, for it enjoyed a high level of civilization.", "start": 35.215, "end": 41.436, "zh": "这座城市想必曾经繁荣一时,因为它的文明程度相当高。", "zh_hant": "這座城市想必曾經繁榮一時,因為它的文明程度相當高。"}, {"index": 9, "text": "Houses -- often three storeys high -- were built of stone.", "start": 42.256, "end": 46.596, "zh": "房屋——常常有三层楼高——都是用石头建造的。", "zh_hant": "房屋——常常有三層樓高——都是用石頭建造的。"}, {"index": 10, "text": "They had large rooms with beautifully decorated walls.", "start": 47.656, "end": 51.297, "zh": "屋内房间宽敞,墙壁装饰精美。", "zh_hant": "屋內房間寬敞,牆壁裝飾精美。"}, {"index": 11, "text": "The city was even equipped with a drainage system,", "start": 52.197, "end": 55.117, "zh": "这座城市甚至配备了排水系统,", "zh_hant": "這座城市甚至配備了排水系統,"}, {"index": 12, "text": "for a great many clay pipes were found beneath the narrow streets.", "start": 55.537, "end": 59.218, "zh": "因为在狭窄的街道下面发现了大量陶管。", "zh_hant": "因為在狹窄的街道下面發現了大量陶管。"}, {"index": 13, "text": "The temple which the archaeologists explored", "start": 60.978, "end": 63.939, "zh": "考古学家们探查的这座神庙", "zh_hant": "考古學家們探查的這座神廟"}, {"index": 14, "text": "was used as a place of worship from the fifteenth century B.C.", "start": 64.299, "end": 68.359, "zh": "从公元前十五世纪起就被用作祭祀场所,", "zh_hant": "從公元前十五世紀起就被用作祭祀場所,"}, {"index": 15, "text": "until Roman times.", "start": 68.799, "end": 70.239, "zh": "一直沿用到罗马时代。", "zh_hant": "一直沿用到羅馬時代。"}, {"index": 16, "text": "In the most sacred room of the temple, clay fragments of fifteen statues were found.", "start": 71.04, "end": 76.74, "zh": "在神庙最神圣的房间里,发现了十五尊雕像的陶土碎片。", "zh_hant": "在神廟最神聖的房間裡,發現了十五尊雕像的陶土碎片。"}, {"index": 17, "text": "Each of these represented a goddess and had, at one time, been painted.", "start": 77.92, "end": 83.481, "zh": "每一尊都代表一位女神,而且都曾经上过彩。", "zh_hant": "每一尊都代表一位女神,而且都曾經上過彩。"}, {"index": 18, "text": "The body of one statue was found among remains dating from the 15th century B.C.", "start": 84.801, "end": 90.422, "zh": "其中一尊雕像的身躯是在公元前十五世纪的遗迹中发现的。", "zh_hant": "其中一尊雕像的身軀是在公元前十五世紀的遺蹟中發現的。"}, {"index": 19, "text": "Its missing head happened to be among remains of the fifth century B.C.", "start": 91.922, "end": 96.363, "zh": "而它遗失的头部却恰好出现在公元前五世纪的遗迹中。", "zh_hant": "而它遺失的頭部卻恰好出現在公元前五世紀的遺蹟中。"}, {"index": 20, "text": "This head must have been found in Classical times and carefully preserved.", "start": 98.123, "end": 103.224, "zh": "这个头部想必是在古典时期被发现,并被精心保存了下来。", "zh_hant": "這個頭部想必是在古典時期被發現,並被精心儲存了下來。"}, {"index": 21, "text": "It was very old and precious even then.", "start": 104.284, "end": 107.184, "zh": "即使在那时,它也已经是十分古老而珍贵的了。", "zh_hant": "即使在那時,它也已經是十分古老而珍貴的了。"}, {"index": 22, "text": "When the archaeologists reconstructed the fragments,", "start": 108.404, "end": 111.525, "zh": "当考古学家们把碎片拼接复原时,", "zh_hant": "當考古學家們把碎片拼接復原時,"}, {"index": 23, "text": "they were amazed to find that the goddess turned out to be a very modern-looking woman.", "start": 111.945, "end": 117.366, "zh": "他们惊讶地发现,这位女神看起来竟像个非常现代的女性。", "zh_hant": "他們驚訝地發現,這位女神看起來竟像個非常現代的女性。"}, {"index": 24, "text": "She stood three feet high and her hands rested on her hips.", "start": 118.526, "end": 122.706, "zh": "她高三英尺,双手叉在腰间。", "zh_hant": "她高三英尺,雙手叉在腰間。"}, {"index": 25, "text": "She was wearing a full-length skirt which swept the ground.", "start": 123.407, "end": 127.187, "zh": "她穿着一条曳地的长裙。", "zh_hant": "她穿著一條曳地的長裙。"}, {"index": 26, "text": "Despite her great age, she was very graceful indeed,", "start": 128.107, "end": 131.948, "zh": "尽管年代久远,她的姿态依然十分优雅,", "zh_hant": "儘管年代久遠,她的姿態依然十分優雅,"}, {"index": 27, "text": "but, so far, the archaeologists have been unable to discover her identity.", "start": 132.388, "end": 137.388, "zh": "但到目前为止,考古学家们仍未能查明她的身份。", "zh_hant": "但到目前為止,考古學家們仍未能查明她的身份。"}]