[{"index": 0, "text": "Why did the writer become very worried?", "start": 15.072, "end": 18.233}, {"index": 1, "text": "Dentists always ask questions when it is impossible for you to answer.", "start": 21.255, "end": 26.337}, {"index": 2, "text": "My dentist had just pulled out one of my teeth and had told me to rest for a while.", "start": 27.838, "end": 33.02}, {"index": 3, "text": "I tried to say something,", "start": 34.641, "end": 36.042}, {"index": 4, "text": "but my mouth was full of cotton wool.", "start": 36.562, "end": 38.743}, {"index": 5, "text": "He knew I collected match boxes and asked me whether my collection was growing.", "start": 40.884, "end": 46.972}, {"index": 6, "text": "He then asked me how my brother was and whether I liked my new job in London.", "start": 48.173, "end": 53.175}, {"index": 7, "text": "In answer to these questions I either nodded or made strange noises.", "start": 54.896, "end": 60.099}, {"index": 8, "text": "Meanwhile, my tongue was busy searching out the hole where the tooth had been.", "start": 61.36, "end": 66.863}, {"index": 9, "text": "I suddenly felt very worried, but could not say anything.", "start": 68.644, "end": 72.205}, {"index": 10, "text": "When the dentist at last removed the cotton wool from my mouth,", "start": 73.748, "end": 77.676}, {"index": 11, "text": "I was able to tell him that he had pulled out the wrong tooth.", "start": 78.819, "end": 82.246}]